MANIFEST.in
README.md
setup.py
daj/__init__.py
daj/daj.py
daj.egg-info/PKG-INFO
daj.egg-info/SOURCES.txt
daj.egg-info/dependency_links.txt
daj.egg-info/not-zip-safe
daj.egg-info/requires.txt
daj.egg-info/top_level.txt