Metadata-Version: 1.1
Name: daj
Version: 0.1.0
Summary: Read and write data without further ado.
Home-page: https://github.com/Yomguithereal/python-daj
Author: Yomguithereal
Author-email: UNKNOWN
License: MIT License
Keywords: data json yaml csv read write file
Platform: UNKNOWN
Classifier: Programming Language :: Python :: 2.6
Classifier: Programming Language :: Python :: 2.7
Classifier: Programming Language :: Python :: 3.3
Classifier: Programming Language :: Python :: 3.4
Classifier: Topic :: Utilities
